BenbanfaXuePython/README.md
BenbanfaXuePython/__init__.py
BenbanfaXuePython/__main__.py
BenbanfaXuePython/file.epub
BenbanfaXuePython/index.html
BenbanfaXuePython/css/__init__.py
BenbanfaXuePython/css/annotations.css
BenbanfaXuePython/css/main.css
BenbanfaXuePython/css/normalize.css
BenbanfaXuePython/css/popup.css
BenbanfaXuePython/font/__init__.py
BenbanfaXuePython/font/fontello.eot
BenbanfaXuePython/font/fontello.svg
BenbanfaXuePython/font/fontello.ttf
BenbanfaXuePython/font/fontello.woff
BenbanfaXuePython/img/__init__.py
BenbanfaXuePython/img/annotator-glyph-sprite.png
BenbanfaXuePython/img/annotator-icon-sprite.png
BenbanfaXuePython/img/apple-touch-icon.png
BenbanfaXuePython/img/cancelfullscreen.png
BenbanfaXuePython/img/close.png
BenbanfaXuePython/img/fullscreen.png
BenbanfaXuePython/img/loader.gif
BenbanfaXuePython/img/menu-icon.png
BenbanfaXuePython/img/save.png
BenbanfaXuePython/img/saved.png
BenbanfaXuePython/img/settings-s.png
BenbanfaXuePython/img/settings.png
BenbanfaXuePython/img/star.png
BenbanfaXuePython/js/__init__.py
BenbanfaXuePython/js/epub.js
BenbanfaXuePython/js/epub.min.js
BenbanfaXuePython/js/epub.min.map
BenbanfaXuePython/js/hooks.min.js
BenbanfaXuePython/js/hooks.min.map
BenbanfaXuePython/js/reader.js
BenbanfaXuePython/js/reader.js.map
BenbanfaXuePython/js/reader.min.js
BenbanfaXuePython/js/reader.min.map
BenbanfaXuePython/js/hooks/__init__.py
BenbanfaXuePython/js/hooks/extensions/__init__.py
BenbanfaXuePython/js/hooks/extensions/highlight.js
BenbanfaXuePython/js/libs/__init__.py
BenbanfaXuePython/js/libs/jquery.min.js
BenbanfaXuePython/js/libs/localforage.min.js
BenbanfaXuePython/js/libs/screenfull.js
BenbanfaXuePython/js/libs/screenfull.min.js
BenbanfaXuePython/js/libs/zip.min.js
BenbanfaXuePython/js/plugins/__init__.py
BenbanfaXuePython/js/plugins/hypothesis.js
BenbanfaXuePython/js/plugins/search.js
benbanfa_xue_python-2024.3.1.0.dist-info/METADATA
benbanfa_xue_python-2024.3.1.0.dist-info/WHEEL
benbanfa_xue_python-2024.3.1.0.dist-info/entry_points.txt
benbanfa_xue_python-2024.3.1.0.dist-info/top_level.txt
benbanfa_xue_python-2024.3.1.0.dist-info/RECORD
